LICENSE.txt
README.rst
setup.cfg
setup.py
.idea/doc-manager.iml
.idea/misc.xml
.idea/modules.xml
.idea/vcs.xml
.idea/libraries/R_User_Library.xml
mongo_connector/__init__.py
mongo_connector/doc_managers/__init__.py
mongo_connector/doc_managers/new_neo4j_doc_manager.py
mongo_connector/doc_managers/nodes_and_relationships_builder.py
mongo_connector/doc_managers/nodes_and_relationships_updater.py
mongo_connector/tests/__init__.py
mongo_connector/tests/neo4j_doc_manager.py
mongo_connector/tests/test_neio4j_doc_mangager.py
new_neo4j_doc_manager.egg-info/PKG-INFO
new_neo4j_doc_manager.egg-info/SOURCES.txt
new_neo4j_doc_manager.egg-info/dependency_links.txt
new_neo4j_doc_manager.egg-info/entry_points.txt
new_neo4j_doc_manager.egg-info/requires.txt
new_neo4j_doc_manager.egg-info/top_level.txt