Metadata-Version: 1.1
Name: new-neo4j-doc-manager
Version: 3.0.1
Summary: Neo4j Doc manager for Mongo Connector
Home-page: https://gitee.com/Smarter_KYQ/Neo4j_doc-manager.git
Author: Smarter_KYQ
Author-email: keyuqiangsmarter@163.com
License: Apache Software License
Platform: UNKNOWN
Classifier: Development Status :: 5 - Production/Stable
Classifier: Intended Audience :: Developers
Classifier: License :: OSI Approved :: Apache Software License
Classifier: Operating System :: OS Independent
Classifier: Programming Language :: Python :: 2.7
Classifier: Programming Language :: Python :: 3.3
Classifier: Programming Language :: Python :: 3.4
Classifier: Programming Language :: Python :: 3.5
Classifier: Programming Language :: Python :: 3.6
Classifier: Topic :: Database
Classifier: Topic :: Software Development
